django_pagination_widget/__init__.py
django_pagination_widget/apps.py
django_pagination_widget/static/django_pagination_widget/css/pagination.css
django_pagination_widget/static/django_pagination_widget/js/pagination.js
django_pagination_widget/templates/django_pagination_widget/pagination.html
django_pagination_widget/templatetags/__init__.py
django_pagination_widget/templatetags/pagination_tags.py
django_pagination_widget-0.1.2.dist-info/licenses/LICENSE
django_pagination_widget-0.1.2.dist-info/METADATA
django_pagination_widget-0.1.2.dist-info/WHEEL
django_pagination_widget-0.1.2.dist-info/top_level.txt
django_pagination_widget-0.1.2.dist-info/RECORD
