Metadata-Version: 2.4
Name: django-pagination-widget
Version: 0.1.2
Summary: A reusable Django pagination component with modern, clean styling and interactive JavaScript behavior
Home-page: https://github.com/priyesh-04/django-pagination-widget
Author: Priyesh Shukla
Author-email: Priyesh Shukla <priyesh.shukla070@gmail.com>
Maintainer-email: Priyesh Shukla <priyesh.shukla070@gmail.com>
License: MIT
Project-URL: Homepage, https://github.com/priyesh-04/django-pagination-widget
Project-URL: Documentation, https://django-pagination-widget.readthedocs.io/
Project-URL: Repository, https://github.com/priyesh-04/django-pagination-widget
Project-URL: Issues, https://github.com/priyesh-04/django-pagination-widget/issues
Project-URL: Changelog, https://github.com/priyesh-04/django-pagination-widget/blob/main/CHANGELOG.md
Keywords: django,pagination,widget,modern,javascript
Classifier: Development Status :: 3 - Alpha
Classifier: Environment :: Web Environment
Classifier: Framework :: Django
Classifier: Framework :: Django :: 4.2
Classifier: Framework :: Django :: 5.0
Classifier: Framework :: Django :: 5.1
Classifier: Framework :: Django :: 5.2
Classifier: Intended Audience :: Developers
Classifier: License :: OSI Approved :: MIT License
Classifier: Operating System :: OS Independent
Classifier: Programming Language :: Python
Classifier: Programming Language :: Python :: 3
Classifier: Programming Language :: Python :: 3.8
Classifier: Programming Language :: Python :: 3.9
Classifier: Programming Language :: Python :: 3.10
Classifier: Programming Language :: Python :: 3.11
Classifier: Programming Language :: Python :: 3.12
Classifier: Programming Language :: Python :: 3.13
Classifier: Topic :: Internet :: WWW/HTTP
Classifier: Topic :: Internet :: WWW/HTTP :: Dynamic Content
Requires-Python: >=3.8
License-File: LICENSE
Requires-Dist: Django>=4.2
Requires-Dist: tzdata; platform_system == "Windows"
Dynamic: author
Dynamic: home-page
Dynamic: license-file
Dynamic: requires-python
